{
  "nodes": [
    {
      "id": "Unknown.if",
      "label": "Unknown.if",
      "file": "..\\react\\packages\\react\\index.experimental.development.js",
      "line": 69
    },
    {
      "id": "getTaskName",
      "label": "getTaskName",
      "file": "..\\react\\packages\\react\\src\\jsx\\ReactJSXElement.js",
      "line": 29
    },
    {
      "id": "getOwner",
      "label": "getOwner",
      "file": "..\\react\\packages\\react\\src\\jsx\\ReactJSXElement.js",
      "line": 50
    },
    {
      "id": "UnknownOwner",
      "label": "UnknownOwner",
      "file": "..\\react\\packages\\react\\src\\jsx\\ReactJSXElement.js",
      "line": 70
    },
    {
      "id": "hasValidRef",
      "label": "hasValidRef",
      "file": "..\\react\\packages\\react\\src\\jsx\\ReactJSXElement.js",
      "line": 97
    },
    {
      "id": "hasValidKey",
      "label": "hasValidKey",
      "file": "..\\react\\packages\\react\\src\\jsx\\ReactJSXElement.js",
      "line": 109
    },
    {
      "id": "defineKeyPropWarningGetter",
      "label": "defineKeyPropWarningGetter",
      "file": "..\\react\\packages\\react\\src\\jsx\\ReactJSXElement.js",
      "line": 121
    },
    {
      "id": "elementRefGetterWithDeprecationWarning",
      "label": "elementRefGetterWithDeprecationWarning",
      "file": "..\\react\\packages\\react\\src\\jsx\\ReactJSXElement.js",
      "line": 143
    },
    {
      "id": "ReactElement",
      "label": "ReactElement",
      "file": "..\\react\\packages\\react\\src\\jsx\\ReactJSXElement.js",
      "line": 170
    },
    {
      "id": "jsxProd",
      "label": "jsxProd",
      "file": "..\\react\\packages\\react\\src\\jsx\\ReactJSXElement.js",
      "line": 291
    },
    {
      "id": "jsxProdSignatureRunningInDevWithDynamicChildren",
      "label": "jsxProdSignatureRunningInDevWithDynamicChildren",
      "file": "..\\react\\packages\\react\\src\\jsx\\ReactJSXElement.js",
      "line": 362
    },
    {
      "id": "jsxProdSignatureRunningInDevWithStaticChildren",
      "label": "jsxProdSignatureRunningInDevWithStaticChildren",
      "file": "..\\react\\packages\\react\\src\\jsx\\ReactJSXElement.js",
      "line": 398
    },
    {
      "id": "jsxDEV",
      "label": "jsxDEV",
      "file": "..\\react\\packages\\react\\src\\jsx\\ReactJSXElement.js",
      "line": 441
    },
    {
      "id": "jsxDEVImpl",
      "label": "jsxDEVImpl",
      "file": "..\\react\\packages\\react\\src\\jsx\\ReactJSXElement.js",
      "line": 469
    },
    {
      "id": "createElement",
      "label": "createElement",
      "file": "..\\react\\packages\\react\\src\\jsx\\ReactJSXElement.js",
      "line": 610
    },
    {
      "id": "cloneAndReplaceKey",
      "label": "cloneAndReplaceKey",
      "file": "..\\react\\packages\\react\\src\\jsx\\ReactJSXElement.js",
      "line": 748
    },
    {
      "id": "cloneElement",
      "label": "cloneElement",
      "file": "..\\react\\packages\\react\\src\\jsx\\ReactJSXElement.js",
      "line": 770
    },
    {
      "id": "validateChildKeys",
      "label": "validateChildKeys",
      "file": "..\\react\\packages\\react\\src\\jsx\\ReactJSXElement.js",
      "line": 865
    },
    {
      "id": "isValidElement",
      "label": "isValidElement",
      "file": "..\\react\\packages\\react\\src\\jsx\\ReactJSXElement.js",
      "line": 892
    },
    {
      "id": "isLazyType",
      "label": "isLazyType",
      "file": "..\\react\\packages\\react\\src\\jsx\\ReactJSXElement.js",
      "line": 900
    },
    {
      "id": "Component",
      "label": "Component",
      "file": "..\\react\\packages\\react\\src\\ReactBaseClasses.js",
      "line": 19
    },
    {
      "id": "ComponentDummy",
      "label": "ComponentDummy",
      "file": "..\\react\\packages\\react\\src\\ReactBaseClasses.js",
      "line": 126
    },
    {
      "id": "PureComponent",
      "label": "PureComponent",
      "file": "..\\react\\packages\\react\\src\\ReactBaseClasses.js",
      "line": 132
    },
    {
      "id": "escape",
      "label": "escape",
      "file": "..\\react\\packages\\react\\src\\ReactChildren.js",
      "line": 41
    },
    {
      "id": "escapeUserProvidedKey",
      "label": "escapeUserProvidedKey",
      "file": "..\\react\\packages\\react\\src\\ReactChildren.js",
      "line": 63
    },
    {
      "id": "getElementKey",
      "label": "getElementKey",
      "file": "..\\react\\packages\\react\\src\\ReactChildren.js",
      "line": 74
    },
    {
      "id": "createRef",
      "label": "createRef",
      "file": "..\\react\\packages\\react\\src\\ReactCreateRef.js",
      "line": 12
    },
    {
      "id": "warnNoop",
      "label": "warnNoop",
      "file": "..\\react\\packages\\react\\src\\ReactNoopUpdateQueue.js",
      "line": 10
    },
    {
      "id": "releaseAsyncTransition",
      "label": "releaseAsyncTransition",
      "file": "..\\react\\packages\\react\\src\\ReactStartTransition.js",
      "line": 39
    },
    {
      "id": "Unknown.onStartTransitionFinish",
      "label": "Unknown.onStartTransitionFinish",
      "file": "..\\react\\packages\\react\\src\\ReactStartTransition.js",
      "line": 79
    },
    {
      "id": "warnAboutTransitionSubscriptions",
      "label": "warnAboutTransitionSubscriptions",
      "file": "..\\react\\packages\\react\\src\\ReactStartTransition.js",
      "line": 185
    }
  ],
  "edges": [
    {
      "from": "getTaskName",
      "to": "getComponentNameFromType",
      "file": "..\\react\\packages\\react\\src\\jsx\\ReactJSXElement.js",
      "line": 43
    },
    {
      "from": "getOwner",
      "to": "getOwner",
      "file": "..\\react\\packages\\react\\src\\jsx\\ReactJSXElement.js",
      "line": 56
    },
    {
      "from": "UnknownOwner",
      "to": "Error",
      "file": "..\\react\\packages\\react\\src\\jsx\\ReactJSXElement.js",
      "line": 72
    },
    {
      "from": "hasValidRef",
      "to": "call",
      "file": "..\\react\\packages\\react\\src\\jsx\\ReactJSXElement.js",
      "line": 99
    },
    {
      "from": "hasValidRef",
      "to": "getOwnPropertyDescriptor",
      "file": "..\\react\\packages\\react\\src\\jsx\\ReactJSXElement.js",
      "line": 100
    },
    {
      "from": "hasValidKey",
      "to": "call",
      "file": "..\\react\\packages\\react\\src\\jsx\\ReactJSXElement.js",
      "line": 111
    },
    {
      "from": "hasValidKey",
      "to": "getOwnPropertyDescriptor",
      "file": "..\\react\\packages\\react\\src\\jsx\\ReactJSXElement.js",
      "line": 112
    },
    {
      "from": "defineKeyPropWarningGetter",
      "to": "error",
      "file": "..\\react\\packages\\react\\src\\jsx\\ReactJSXElement.js",
      "line": 126
    },
    {
      "from": "defineKeyPropWarningGetter",
      "to": "defineProperty",
      "file": "..\\react\\packages\\react\\src\\jsx\\ReactJSXElement.js",
      "line": 136
    },
    {
      "from": "elementRefGetterWithDeprecationWarning",
      "to": "getComponentNameFromType",
      "file": "..\\react\\packages\\react\\src\\jsx\\ReactJSXElement.js",
      "line": 145
    },
    {
      "from": "elementRefGetterWithDeprecationWarning",
      "to": "error",
      "file": "..\\react\\packages\\react\\src\\jsx\\ReactJSXElement.js",
      "line": 148
    },
    {
      "from": "ReactElement",
      "to": "defineProperty",
      "file": "..\\react\\packages\\react\\src\\jsx\\ReactJSXElement.js",
      "line": 202
    },
    {
      "from": "ReactElement",
      "to": "defineProperty",
      "file": "..\\react\\packages\\react\\src\\jsx\\ReactJSXElement.js",
      "line": 220
    },
    {
      "from": "ReactElement",
      "to": "defineProperty",
      "file": "..\\react\\packages\\react\\src\\jsx\\ReactJSXElement.js",
      "line": 251
    },
    {
      "from": "ReactElement",
      "to": "defineProperty",
      "file": "..\\react\\packages\\react\\src\\jsx\\ReactJSXElement.js",
      "line": 258
    },
    {
      "from": "ReactElement",
      "to": "defineProperty",
      "file": "..\\react\\packages\\react\\src\\jsx\\ReactJSXElement.js",
      "line": 264
    },
    {
      "from": "ReactElement",
      "to": "defineProperty",
      "file": "..\\react\\packages\\react\\src\\jsx\\ReactJSXElement.js",
      "line": 270
    },
    {
      "from": "ReactElement",
      "to": "freeze",
      "file": "..\\react\\packages\\react\\src\\jsx\\ReactJSXElement.js",
      "line": 277
    },
    {
      "from": "ReactElement",
      "to": "freeze",
      "file": "..\\react\\packages\\react\\src\\jsx\\ReactJSXElement.js",
      "line": 278
    },
    {
      "from": "jsxProd",
      "to": "checkKeyStringCoercion",
      "file": "..\\react\\packages\\react\\src\\jsx\\ReactJSXElement.js",
      "line": 305
    },
    {
      "from": "jsxProd",
      "to": "hasValidKey",
      "file": "..\\react\\packages\\react\\src\\jsx\\ReactJSXElement.js",
      "line": 311
    },
    {
      "from": "jsxProd",
      "to": "checkKeyStringCoercion",
      "file": "..\\react\\packages\\react\\src\\jsx\\ReactJSXElement.js",
      "line": 316
    },
    {
      "from": "jsxProd",
      "to": "ReactElement",
      "file": "..\\react\\packages\\react\\src\\jsx\\ReactJSXElement.js",
      "line": 347
    },
    {
      "from": "jsxProd",
      "to": "getOwner",
      "file": "..\\react\\packages\\react\\src\\jsx\\ReactJSXElement.js",
      "line": 347
    },
    {
      "from": "jsxProdSignatureRunningInDevWithDynamicChildren",
      "to": "Error",
      "file": "..\\react\\packages\\react\\src\\jsx\\ReactJSXElement.js",
      "line": 377
    },
    {
      "from": "jsxProdSignatureRunningInDevWithDynamicChildren",
      "to": "jsxDEVImpl",
      "file": "..\\react\\packages\\react\\src\\jsx\\ReactJSXElement.js",
      "line": 384
    },
    {
      "from": "jsxProdSignatureRunningInDevWithDynamicChildren",
      "to": "createTask",
      "file": "..\\react\\packages\\react\\src\\jsx\\ReactJSXElement.js",
      "line": 392
    },
    {
      "from": "jsxProdSignatureRunningInDevWithDynamicChildren",
      "to": "getTaskName",
      "file": "..\\react\\packages\\react\\src\\jsx\\ReactJSXElement.js",
      "line": 392
    },
    {
      "from": "jsxProdSignatureRunningInDevWithStaticChildren",
      "to": "Error",
      "file": "..\\react\\packages\\react\\src\\jsx\\ReactJSXElement.js",
      "line": 413
    },
    {
      "from": "jsxProdSignatureRunningInDevWithStaticChildren",
      "to": "jsxDEVImpl",
      "file": "..\\react\\packages\\react\\src\\jsx\\ReactJSXElement.js",
      "line": 419
    },
    {
      "from": "jsxProdSignatureRunningInDevWithStaticChildren",
      "to": "createTask",
      "file": "..\\react\\packages\\react\\src\\jsx\\ReactJSXElement.js",
      "line": 427
    },
    {
      "from": "jsxProdSignatureRunningInDevWithStaticChildren",
      "to": "getTaskName",
      "file": "..\\react\\packages\\react\\src\\jsx\\ReactJSXElement.js",
      "line": 427
    },
    {
      "from": "jsxDEV",
      "to": "Error",
      "file": "..\\react\\packages\\react\\src\\jsx\\ReactJSXElement.js",
      "line": 450
    },
    {
      "from": "jsxDEV",
      "to": "jsxDEVImpl",
      "file": "..\\react\\packages\\react\\src\\jsx\\ReactJSXElement.js",
      "line": 456
    },
    {
      "from": "jsxDEV",
      "to": "createTask",
      "file": "..\\react\\packages\\react\\src\\jsx\\ReactJSXElement.js",
      "line": 464
    },
    {
      "from": "jsxDEV",
      "to": "getTaskName",
      "file": "..\\react\\packages\\react\\src\\jsx\\ReactJSXElement.js",
      "line": 464
    },
    {
      "from": "jsxDEVImpl",
      "to": "isArray",
      "file": "..\\react\\packages\\react\\src\\jsx\\ReactJSXElement.js",
      "line": 492
    },
    {
      "from": "jsxDEVImpl",
      "to": "validateChildKeys",
      "file": "..\\react\\packages\\react\\src\\jsx\\ReactJSXElement.js",
      "line": 494
    },
    {
      "from": "jsxDEVImpl",
      "to": "freeze",
      "file": "..\\react\\packages\\react\\src\\jsx\\ReactJSXElement.js",
      "line": 498
    },
    {
      "from": "jsxDEVImpl",
      "to": "error",
      "file": "..\\react\\packages\\react\\src\\jsx\\ReactJSXElement.js",
      "line": 501
    },
    {
      "from": "jsxDEVImpl",
      "to": "validateChildKeys",
      "file": "..\\react\\packages\\react\\src\\jsx\\ReactJSXElement.js",
      "line": 508
    },
    {
      "from": "jsxDEVImpl",
      "to": "call",
      "file": "..\\react\\packages\\react\\src\\jsx\\ReactJSXElement.js",
      "line": 513
    },
    {
      "from": "jsxDEVImpl",
      "to": "getComponentNameFromType",
      "file": "..\\react\\packages\\react\\src\\jsx\\ReactJSXElement.js",
      "line": 514
    },
    {
      "from": "jsxDEVImpl",
      "to": "filter",
      "file": "..\\react\\packages\\react\\src\\jsx\\ReactJSXElement.js",
      "line": 515
    },
    {
      "from": "jsxDEVImpl",
      "to": "keys",
      "file": "..\\react\\packages\\react\\src\\jsx\\ReactJSXElement.js",
      "line": 515
    },
    {
      "from": "jsxDEVImpl",
      "to": "join",
      "file": "..\\react\\packages\\react\\src\\jsx\\ReactJSXElement.js",
      "line": 518
    },
    {
      "from": "jsxDEVImpl",
      "to": "join",
      "file": "..\\react\\packages\\react\\src\\jsx\\ReactJSXElement.js",
      "line": 522
    },
    {
      "from": "jsxDEVImpl",
      "to": "error",
      "file": "..\\react\\packages\\react\\src\\jsx\\ReactJSXElement.js",
      "line": 523
    },
    {
      "from": "jsxDEVImpl",
      "to": "checkKeyStringCoercion",
      "file": "..\\react\\packages\\react\\src\\jsx\\ReactJSXElement.js",
      "line": 552
    },
    {
      "from": "jsxDEVImpl",
      "to": "hasValidKey",
      "file": "..\\react\\packages\\react\\src\\jsx\\ReactJSXElement.js",
      "line": 558
    },
    {
      "from": "jsxDEVImpl",
      "to": "checkKeyStringCoercion",
      "file": "..\\react\\packages\\react\\src\\jsx\\ReactJSXElement.js",
      "line": 563
    },
    {
      "from": "jsxDEVImpl",
      "to": "defineKeyPropWarningGetter",
      "file": "..\\react\\packages\\react\\src\\jsx\\ReactJSXElement.js",
      "line": 599
    },
    {
      "from": "jsxDEVImpl",
      "to": "ReactElement",
      "file": "..\\react\\packages\\react\\src\\jsx\\ReactJSXElement.js",
      "line": 602
    },
    {
      "from": "jsxDEVImpl",
      "to": "getOwner",
      "file": "..\\react\\packages\\react\\src\\jsx\\ReactJSXElement.js",
      "line": 602
    },
    {
      "from": "createElement",
      "to": "validateChildKeys",
      "file": "..\\react\\packages\\react\\src\\jsx\\ReactJSXElement.js",
      "line": 622
    },
    {
      "from": "createElement",
      "to": "warn",
      "file": "..\\react\\packages\\react\\src\\jsx\\ReactJSXElement.js",
      "line": 648
    },
    {
      "from": "createElement",
      "to": "hasValidKey",
      "file": "..\\react\\packages\\react\\src\\jsx\\ReactJSXElement.js",
      "line": 656
    },
    {
      "from": "createElement",
      "to": "checkKeyStringCoercion",
      "file": "..\\react\\packages\\react\\src\\jsx\\ReactJSXElement.js",
      "line": 661
    },
    {
      "from": "createElement",
      "to": "call",
      "file": "..\\react\\packages\\react\\src\\jsx\\ReactJSXElement.js",
      "line": 670
    },
    {
      "from": "createElement",
      "to": "Array",
      "file": "..\\react\\packages\\react\\src\\jsx\\ReactJSXElement.js",
      "line": 691
    },
    {
      "from": "createElement",
      "to": "freeze",
      "file": "..\\react\\packages\\react\\src\\jsx\\ReactJSXElement.js",
      "line": 697
    },
    {
      "from": "createElement",
      "to": "defineKeyPropWarningGetter",
      "file": "..\\react\\packages\\react\\src\\jsx\\ReactJSXElement.js",
      "line": 718
    },
    {
      "from": "createElement",
      "to": "Error",
      "file": "..\\react\\packages\\react\\src\\jsx\\ReactJSXElement.js",
      "line": 729
    },
    {
      "from": "createElement",
      "to": "ReactElement",
      "file": "..\\react\\packages\\react\\src\\jsx\\ReactJSXElement.js",
      "line": 735
    },
    {
      "from": "createElement",
      "to": "getOwner",
      "file": "..\\react\\packages\\react\\src\\jsx\\ReactJSXElement.js",
      "line": 739
    },
    {
      "from": "createElement",
      "to": "createTask",
      "file": "..\\react\\packages\\react\\src\\jsx\\ReactJSXElement.js",
      "line": 743
    },
    {
      "from": "createElement",
      "to": "getTaskName",
      "file": "..\\react\\packages\\react\\src\\jsx\\ReactJSXElement.js",
      "line": 743
    },
    {
      "from": "cloneAndReplaceKey",
      "to": "ReactElement",
      "file": "..\\react\\packages\\react\\src\\jsx\\ReactJSXElement.js",
      "line": 749
    },
    {
      "from": "cloneElement",
      "to": "assign",
      "file": "..\\react\\packages\\react\\src\\jsx\\ReactJSXElement.js",
      "line": 780
    },
    {
      "from": "cloneElement",
      "to": "hasValidRef",
      "file": "..\\react\\packages\\react\\src\\jsx\\ReactJSXElement.js",
      "line": 789
    },
    {
      "from": "cloneElement",
      "to": "getOwner",
      "file": "..\\react\\packages\\react\\src\\jsx\\ReactJSXElement.js",
      "line": 790
    },
    {
      "from": "cloneElement",
      "to": "hasValidKey",
      "file": "..\\react\\packages\\react\\src\\jsx\\ReactJSXElement.js",
      "line": 792
    },
    {
      "from": "cloneElement",
      "to": "checkKeyStringCoercion",
      "file": "..\\react\\packages\\react\\src\\jsx\\ReactJSXElement.js",
      "line": 797
    },
    {
      "from": "cloneElement",
      "to": "call",
      "file": "..\\react\\packages\\react\\src\\jsx\\ReactJSXElement.js",
      "line": 806
    },
    {
      "from": "cloneElement",
      "to": "Array",
      "file": "..\\react\\packages\\react\\src\\jsx\\ReactJSXElement.js",
      "line": 833
    },
    {
      "from": "cloneElement",
      "to": "ReactElement",
      "file": "..\\react\\packages\\react\\src\\jsx\\ReactJSXElement.js",
      "line": 840
    },
    {
      "from": "cloneElement",
      "to": "validateChildKeys",
      "file": "..\\react\\packages\\react\\src\\jsx\\ReactJSXElement.js",
      "line": 850
    },
    {
      "from": "validateChildKeys",
      "to": "isValidElement",
      "file": "..\\react\\packages\\react\\src\\jsx\\ReactJSXElement.js",
      "line": 869
    },
    {
      "from": "validateChildKeys",
      "to": "isLazyType",
      "file": "..\\react\\packages\\react\\src\\jsx\\ReactJSXElement.js",
      "line": 873
    },
    {
      "from": "validateChildKeys",
      "to": "isValidElement",
      "file": "..\\react\\packages\\react\\src\\jsx\\ReactJSXElement.js",
      "line": 875
    },
    {
      "from": "escape",
      "to": "replace",
      "file": "..\\react\\packages\\react\\src\\ReactChildren.js",
      "line": 47
    },
    {
      "from": "escapeUserProvidedKey",
      "to": "replace",
      "file": "..\\react\\packages\\react\\src\\ReactChildren.js",
      "line": 64
    },
    {
      "from": "getElementKey",
      "to": "error",
      "file": "..\\react\\packages\\react\\src\\ReactChildren.js",
      "line": 81
    },
    {
      "from": "getElementKey",
      "to": "toString",
      "file": "..\\react\\packages\\react\\src\\ReactChildren.js",
      "line": 83
    },
    {
      "from": "getElementKey",
      "to": "checkKeyStringCoercion",
      "file": "..\\react\\packages\\react\\src\\ReactChildren.js",
      "line": 87
    },
    {
      "from": "getElementKey",
      "to": "escape",
      "file": "..\\react\\packages\\react\\src\\ReactChildren.js",
      "line": 89
    },
    {
      "from": "getElementKey",
      "to": "toString",
      "file": "..\\react\\packages\\react\\src\\ReactChildren.js",
      "line": 92
    },
    {
      "from": "createRef",
      "to": "seal",
      "file": "..\\react\\packages\\react\\src\\ReactCreateRef.js",
      "line": 17
    },
    {
      "from": "warnNoop",
      "to": "error",
      "file": "..\\react\\packages\\react\\src\\ReactNoopUpdateQueue.js",
      "line": 20
    },
    {
      "from": "warnAboutTransitionSubscriptions",
      "to": "clear",
      "file": "..\\react\\packages\\react\\src\\ReactStartTransition.js",
      "line": 192
    },
    {
      "from": "warnAboutTransitionSubscriptions",
      "to": "warn",
      "file": "..\\react\\packages\\react\\src\\ReactStartTransition.js",
      "line": 194
    }
  ]
}